py2app/__init__.py
py2app/build_app.py
py2app/create_appbundle.py
py2app/create_pluginbundle.py
py2app/decorators.py
py2app/filters.py
py2app/script_py2applet.py
py2app/util.py
py2app/apptemplate/__init__.py
py2app/apptemplate/plist_template.py
py2app/apptemplate/setup.py
py2app/apptemplate/lib/__error__.sh
py2app/apptemplate/lib/site.py
py2app/apptemplate/prebuilt/main-fat
py2app/apptemplate/prebuilt/main-fat3
py2app/apptemplate/prebuilt/main-i386
py2app/apptemplate/prebuilt/main-intel
py2app/apptemplate/prebuilt/main-ppc
py2app/apptemplate/prebuilt/main-ppc64
py2app/apptemplate/prebuilt/main-universal
py2app/apptemplate/prebuilt/main-x86_64
py2app/apptemplate/prebuilt/secondary-fat
py2app/apptemplate/prebuilt/secondary-fat3
py2app/apptemplate/prebuilt/secondary-i386
py2app/apptemplate/prebuilt/secondary-intel
py2app/apptemplate/prebuilt/secondary-ppc
py2app/apptemplate/prebuilt/secondary-ppc64
py2app/apptemplate/prebuilt/secondary-universal
py2app/apptemplate/prebuilt/secondary-x86_64
py2app/apptemplate/src/main.c
py2app/bootstrap/__init__.py
py2app/bootstrap/argv_emulation.py
py2app/bootstrap/argv_inject.py
py2app/bootstrap/boot_aliasapp.py
py2app/bootstrap/boot_aliasplugin.py
py2app/bootstrap/boot_app.py
py2app/bootstrap/boot_plugin.py
py2app/bootstrap/chdir_resource.py
py2app/bootstrap/ctypes_setup.py
py2app/bootstrap/disable_linecache.py
py2app/bootstrap/emulate_shell_environment.py
py2app/bootstrap/import_encodings.py
py2app/bootstrap/path_inject.py
py2app/bootstrap/reset_sys_path.py
py2app/bootstrap/semi_standalone_path.py
py2app/bootstrap/setup_included_subpackages.py
py2app/bootstrap/setup_pkgresource.py
py2app/bootstrap/site_packages.py
py2app/bootstrap/system_path_extras.py
py2app/bootstrap/virtualenv.py
py2app/bootstrap/virtualenv_site_packages.py
py2app/bundletemplate/__init__.py
py2app/bundletemplate/plist_template.py
py2app/bundletemplate/setup.py
py2app/bundletemplate/lib/__error__.sh
py2app/bundletemplate/lib/site.py
py2app-0.20.dist-info/LICENSE.txt
py2app-0.20.dist-info/METADATA
py2app-0.20.dist-info/WHEEL
py2app-0.20.dist-info/entry_points.txt
py2app-0.20.dist-info/top_level.txt
py2app-0.20.dist-info/RECORD
