Metadata-Version: 2.1
Name: py2app
Version: 0.20
Summary: Create standalone Mac OS X applications with Python
Home-page: http://bitbucket.org/ronaldoussoren/py2app
Author: Ronald Oussoren
Author-email: ronaldoussoren@mac.com
Maintainer: Ronald Oussoren
Maintainer-email: ronaldoussoren@mac.com
License: MIT or PSF License
Download-URL: http://pypi.python.org/pypi/py2app
Keywords: .app,standalone
Platform: MacOS X
Classifier: Development Status :: 4 - Beta
Classifier: Environment :: Console
Classifier: Environment :: MacOS X :: Cocoa
Classifier: Intended Audience :: Developers
Classifier: License :: OSI Approved :: MIT License
Classifier: Natural Language :: English
Classifier: Operating System :: MacOS :: MacOS X
Classifier: Programming Language :: Python
Classifier: Programming Language :: Python :: 2
Classifier: Programming Language :: Python :: 2.7
Classifier: Programming Language :: Python :: 3
Classifier: Programming Language :: Python :: 3.6
Classifier: Programming Language :: Python :: 3.7
Classifier: Programming Language :: Python :: 3.8
Classifier: Programming Language :: Objective C
Classifier: Topic :: Software Development :: Libraries :: Python Modules
Classifier: Topic :: Software Development :: User Interfaces
Classifier: Topic :: Software Development :: Build Tools
Project-URL: Documentation, https://py2app.readthedocs.io/en/latest/
Project-URL: Issue tracker, https://github.com/ronaldoussoren/py2app/issues
Project-URL: Repository, https://github.com/ronaldoussoren/py2app
Requires-Dist: altgraph (>=0.16)
Requires-Dist: modulegraph (>=0.17)
Requires-Dist: macholib (>=1.11)
